jiosaavnpy/__init__.py
jiosaavnpy/endpoints.py
jiosaavnpy/functions.py
jiosaavnpy/jiosaavn.py
jiosaavnpy/albums/albums.py
jiosaavnpy/artists/artists.py
jiosaavnpy/home/home.py
jiosaavnpy/playlists/playlists.py
jiosaavnpy/songs/songs.py
jiosaavnpy-0.1.3.dist-info/METADATA
jiosaavnpy-0.1.3.dist-info/WHEEL
jiosaavnpy-0.1.3.dist-info/licenses/LICENSE
jiosaavnpy-0.1.3.dist-info/RECORD
