Metadata-Version: 2.4
Name: jiosaavnpy
Version: 0.1.3
Summary: An unofficial Python wrapper for Jiosaavn.
Project-URL: Homepage, https://github.com/ZingyTomato/JiosaavnPy
Project-URL: Repository, https://github.com/ZingyTomato/JiosaavnPy/
Project-URL: Issues, https://github.com/ZingyTomato/JiosaavnPy/issues
Author: ZingyTomato
License:                     GNU GENERAL PUBLIC LICENSE
License-File: LICENSE
Keywords: api,audio,jiosaavn,music,streaming
Classifier: Development Status :: 4 - Beta
Classifier: Intended Audience :: Developers
Classifier: Intended Audience :: Science/Research
Classifier: License :: OSI Approved :: GNU General Public License v3 or later (GPLv3+)
Classifier: Operating System :: OS Independent
Classifier: Programming Language :: Python :: 3
Classifier: Topic :: Internet
Classifier: Topic :: Scientific/Engineering :: Information Analysis
Classifier: Topic :: Software Development :: Libraries :: Python Modules
Requires-Python: >=3.7
Requires-Dist: pydes>=2.0.1
Requires-Dist: requests>=2.0.0
Provides-Extra: dev
Requires-Dist: pytest; extra == 'dev'
